math_pack/__init__.py
math_pack/math_fun.py
math_function_tamilselvan_13-0.0.1.dist-info/LICENSE
math_function_tamilselvan_13-0.0.1.dist-info/METADATA
math_function_tamilselvan_13-0.0.1.dist-info/WHEEL
math_function_tamilselvan_13-0.0.1.dist-info/top_level.txt
math_function_tamilselvan_13-0.0.1.dist-info/RECORD
